{
"meta":{"test_sets":[],"test_metrics":[],"learn_metrics":[{"best_value":"Min","name":"RMSE"}],"launch_mode":"Train","parameters":"","iteration_count":100,"learn_sets":["learn"],"name":"experiment"},
"iterations":[
{"learn":[14.04902515],"iteration":0,"passed_time":0.001011111101,"remaining_time":0.100099999},
{"learn":[13.20277555],"iteration":1,"passed_time":0.002179574103,"remaining_time":0.106799131},
{"learn":[12.44325007],"iteration":2,"passed_time":0.002867915877,"remaining_time":0.09272928003},
{"learn":[11.73390658],"iteration":3,"passed_time":0.003687465037,"remaining_time":0.08849916089},
{"learn":[11.06616689],"iteration":4,"passed_time":0.004326407963,"remaining_time":0.08220175129},
{"learn":[10.51892195],"iteration":5,"passed_time":0.005005798725,"remaining_time":0.07842418002},
{"learn":[10.06444735],"iteration":6,"passed_time":0.00560105772,"remaining_time":0.07441405257},
{"learn":[9.641791564],"iteration":7,"passed_time":0.006070822245,"remaining_time":0.06981445581},
{"learn":[9.259233732],"iteration":8,"passed_time":0.006530153271,"remaining_time":0.06602710529},
{"learn":[8.867805286],"iteration":9,"passed_time":0.007001806296,"remaining_time":0.06301625666},
{"learn":[8.541878316],"iteration":10,"passed_time":0.007439971824,"remaining_time":0.06019613567},
{"learn":[8.23068324],"iteration":11,"passed_time":0.007799558232,"remaining_time":0.05719676037},
{"learn":[7.995288269],"iteration":12,"passed_time":0.008162971725,"remaining_time":0.05462911847},
{"learn":[7.690141586],"iteration":13,"passed_time":0.008523344117,"remaining_time":0.05235768529},
{"learn":[7.44277432],"iteration":14,"passed_time":0.008869673625,"remaining_time":0.05026148387},
{"learn":[7.237353953],"iteration":15,"passed_time":0.009228629642,"remaining_time":0.04845030562},
{"learn":[7.042411736],"iteration":16,"passed_time":0.009588624735,"remaining_time":0.04681505018},
{"learn":[6.899301849],"iteration":17,"passed_time":0.009950758081,"remaining_time":0.04533123126},
{"learn":[6.750397155],"iteration":18,"passed_time":0.01033125556,"remaining_time":0.0440437737},
{"learn":[6.624954348],"iteration":19,"passed_time":0.01070243875,"remaining_time":0.042809755},
{"learn":[6.502332572],"iteration":20,"passed_time":0.0110361344,"remaining_time":0.04151688656},
{"learn":[6.406868506],"iteration":21,"passed_time":0.01132964733,"remaining_time":0.04016874962},
{"learn":[6.326186865],"iteration":22,"passed_time":0.01162079963,"remaining_time":0.03890441615},
{"learn":[6.237629164],"iteration":23,"passed_time":0.01193210506,"remaining_time":0.03778499937},
{"learn":[6.16670552],"iteration":24,"passed_time":0.0123068913,"remaining_time":0.03692067389},
{"learn":[6.110096564],"iteration":25,"passed_time":0.01266106763,"remaining_time":0.03603534634},
{"learn":[6.050916593],"iteration":26,"passed_time":0.01296842578,"remaining_time":0.03506278081},
{"learn":[5.989007026],"iteration":27,"passed_time":0.0132638252,"remaining_time":0.03410697909},
{"learn":[5.942206352],"iteration":28,"passed_time":0.01356579632,"remaining_time":0.03321281167},
{"learn":[5.884128492],"iteration":29,"passed_time":0.01385484108,"remaining_time":0.03232796252},
{"learn":[5.849279609],"iteration":30,"passed_time":0.01416467672,"remaining_time":0.03152782882},
{"learn":[5.797033387],"iteration":31,"passed_time":0.01444953112,"remaining_time":0.03070525364},
{"learn":[5.756768179],"iteration":32,"passed_time":0.01474657531,"remaining_time":0.02994001653},
{"learn":[5.733248116],"iteration":33,"passed_time":0.01505565501,"remaining_time":0.02922568325},
{"learn":[5.700046492],"iteration":34,"passed_time":0.01535565014,"remaining_time":0.02851763597},
{"learn":[5.68327707],"iteration":35,"passed_time":0.01560877066,"remaining_time":0.02774892561},
{"learn":[5.660542731],"iteration":36,"passed_time":0.01591217884,"remaining_time":0.02709370992},
{"learn":[5.630366322],"iteration":37,"passed_time":0.01620736057,"remaining_time":0.0264435883},
{"learn":[5.623352945],"iteration":38,"passed_time":0.01639352212,"remaining_time":0.02564114999},
{"learn":[5.595248587],"iteration":39,"passed_time":0.01668290145,"remaining_time":0.02502435217},
{"learn":[5.573345849],"iteration":40,"passed_time":0.01699135009,"remaining_time":0.02445096721},
{"learn":[5.559281302],"iteration":41,"passed_time":0.01729684044,"remaining_time":0.02388611299},
{"learn":[5.543396222],"iteration":42,"passed_time":0.01758618237,"remaining_time":0.02331191617},
{"learn":[5.521086585],"iteration":43,"passed_time":0.01788109698,"remaining_time":0.0227577598},
{"learn":[5.492426449],"iteration":44,"passed_time":0.01817677554,"remaining_time":0.022216059},
{"learn":[5.477895422],"iteration":45,"passed_time":0.01846429709,"remaining_time":0.02167547919},
{"learn":[5.461239476],"iteration":46,"passed_time":0.01875516959,"remaining_time":0.02114944655},
{"learn":[5.451830879],"iteration":47,"passed_time":0.01906249434,"remaining_time":0.02065103554},
{"learn":[5.438261293],"iteration":48,"passed_time":0.01955701773,"remaining_time":0.02035526335},
{"learn":[5.429554898],"iteration":49,"passed_time":0.01999048604,"remaining_time":0.01999048604},
{"learn":[5.413146688],"iteration":50,"passed_time":0.02032577103,"remaining_time":0.01952868197},
{"learn":[5.403824947],"iteration":51,"passed_time":0.0206782996,"remaining_time":0.01908766117},
{"learn":[5.395350114],"iteration":52,"passed_time":0.02110334913,"remaining_time":0.01871429074},
{"learn":[5.389798674],"iteration":53,"passed_time":0.02149183667,"remaining_time":0.01830786087},
{"learn":[5.378702661],"iteration":54,"passed_time":0.02183164124,"remaining_time":0.01786225192},
{"learn":[5.358608012],"iteration":55,"passed_time":0.02214960117,"remaining_time":0.01740325806},
{"learn":[5.348834509],"iteration":56,"passed_time":0.02245856,"remaining_time":0.01694242246},
{"learn":[5.344278385],"iteration":57,"passed_time":0.02275520017,"remaining_time":0.01647790357},
{"learn":[5.332299589],"iteration":58,"passed_time":0.02304965802,"remaining_time":0.01601755896},
{"learn":[5.324024877],"iteration":59,"passed_time":0.02335259809,"remaining_time":0.01556839872},
{"learn":[5.310232763],"iteration":60,"passed_time":0.02364016304,"remaining_time":0.0151142026},
{"learn":[5.302820736],"iteration":61,"passed_time":0.02391970987,"remaining_time":0.01466046734},
{"learn":[5.294739854],"iteration":62,"passed_time":0.02422449437,"remaining_time":0.014227084},
{"learn":[5.288924148],"iteration":63,"passed_time":0.02451133144,"remaining_time":0.01378762393},
{"learn":[5.279799584],"iteration":64,"passed_time":0.0248148064,"remaining_time":0.01336181883},
{"learn":[5.274360819],"iteration":65,"passed_time":0.02510767692,"remaining_time":0.01293425781},
{"learn":[5.267507465],"iteration":66,"passed_time":0.02538593293,"remaining_time":0.0125035192},
{"learn":[5.264191227],"iteration":67,"passed_time":0.02568948402,"remaining_time":0.01208916895},
{"learn":[5.255940638],"iteration":68,"passed_time":0.0260324983,"remaining_time":0.01169576011},
{"learn":[5.24998685],"iteration":69,"passed_time":0.02634905721,"remaining_time":0.01129245309},
{"learn":[5.244627233],"iteration":70,"passed_time":0.02666338171,"remaining_time":0.01089067704},
{"learn":[5.239558898],"iteration":71,"passed_time":0.02696713515,"remaining_time":0.01048721922},
{"learn":[5.235264554],"iteration":72,"passed_time":0.02724907066,"remaining_time":0.01007842339},
{"learn":[5.231617027],"iteration":73,"passed_time":0.02770752755,"remaining_time":0.009735077247},
{"learn":[5.22660688],"iteration":74,"passed_time":0.02807385727,"remaining_time":0.009357952422},
{"learn":[5.21798742],"iteration":75,"passed_time":0.02839080683,"remaining_time":0.008965517948},
{"learn":[5.213847377],"iteration":76,"passed_time":0.02867916578,"remaining_time":0.008566504065},
{"learn":[5.202746865],"iteration":77,"passed_time":0.02899519047,"remaining_time":0.008178130644},
{"learn":[5.194754311],"iteration":78,"passed_time":0.02931860154,"remaining_time":0.007793552307},
{"learn":[5.188945348],"iteration":79,"passed_time":0.02962269154,"remaining_time":0.007405672884},
{"learn":[5.181628538],"iteration":80,"passed_time":0.02992045359,"remaining_time":0.007018378002},
{"learn":[5.177831225],"iteration":81,"passed_time":0.03023083347,"remaining_time":0.006636036615},
{"learn":[5.172737434],"iteration":82,"passed_time":0.03052349764,"remaining_time":0.006251800722},
{"learn":[5.161252111],"iteration":83,"passed_time":0.03081208764,"remaining_time":0.005868969075},
{"learn":[5.158693812],"iteration":84,"passed_time":0.03110176147,"remaining_time":0.005488546141},
{"learn":[5.14844995],"iteration":85,"passed_time":0.03140081903,"remaining_time":0.005111761237},
{"learn":[5.144310718],"iteration":86,"passed_time":0.03169282876,"remaining_time":0.004735710045},
{"learn":[5.139012291],"iteration":87,"passed_time":0.03200235188,"remaining_time":0.004363957074},
{"learn":[5.129852617],"iteration":88,"passed_time":0.03230410996,"remaining_time":0.003992642805},
{"learn":[5.125669689],"iteration":89,"passed_time":0.03273773187,"remaining_time":0.003637525764},
{"learn":[5.122378658],"iteration":90,"passed_time":0.03319297671,"remaining_time":0.003282821873},
{"learn":[5.117214953],"iteration":91,"passed_time":0.03361484892,"remaining_time":0.00292303034},
{"learn":[5.11235693],"iteration":92,"passed_time":0.03397077251,"remaining_time":0.002556939867},
{"learn":[5.107334439],"iteration":93,"passed_time":0.03433851794,"remaining_time":0.002191820294},
{"learn":[5.104405965],"iteration":94,"passed_time":0.03497887524,"remaining_time":0.001840993433},
{"learn":[5.100373809],"iteration":95,"passed_time":0.0354014987,"remaining_time":0.001475062446},
{"learn":[5.091849696],"iteration":96,"passed_time":0.03576339632,"remaining_time":0.001106084422},
{"learn":[5.087554598],"iteration":97,"passed_time":0.03610768707,"remaining_time":0.0007368915729},
{"learn":[5.081739613],"iteration":98,"passed_time":0.03639820497,"remaining_time":0.0003676586361},
{"learn":[5.077942791],"iteration":99,"passed_time":0.03668805643,"remaining_time":0}
]}